{"id": "email.errors", "path": "/Users/francois/MyPartage/Programming/python3/hypermodernPython/.nox/mypy-3-7/lib/python3.7/site-packages/mypy/typeshed/stdlib/3/email/errors.pyi", "mtime": 1590603014, "size": 863, "hash": "9083ded03fb23b90351158ed8bc54ad4e5acf9842c6151b148523e4bb70ca8d5", "data_mtime": 1590589491, "dependencies": ["builtins"], "suppressed": [], "options": {"platform": "darwin", "bazel": false, "check_untyped_defs": false, "mypyc": false, "warn_return_any": false, "always_false": [], "strict_optional": true, "strict_equality": false, "implicit_reexport": true, "plugins": [], "ignore_errors": false, "disallow_incomplete_defs": false, "always_true": [], "disallow_subclassing_any": false, "local_partial_types": false, "disallow_any_expr": false, "disallow_any_explicit": false, "warn_unused_ignores": false, "warn_no_return": true, "allow_untyped_globals": false, "follow_imports_for_stubs": false, "disallow_any_generics": false, "no_implicit_optional": false, "follow_imports": "normal", "disallow_any_decorated": false, "warn_unreachable": false, "disallow_untyped_defs": false, "allow_redefinition": false, "disallow_untyped_calls": false, "disallow_any_unimported": false, "strict_optional_whitelist": null, "show_none_errors": true, "ignore_missing_imports": false, "disallow_untyped_decorators": false}, "dep_prios": [5], "dep_lines": [1], "interface_hash": "b611719d47471eeccc3d472dee19267b704827e20c39844c5bf338f9e6f431d0", "version_id": "0.770", "ignore_all": true, "plugin_data": null}
